README.md
setup.py
diadmin/__init__.py
diadmin/copy_policy.py
diadmin/dibackup.py
diadmin/dicatalog.py
diadmin/diconnections.py
diadmin/didockerbuild.py
diadmin/didownload.py
diadmin/didqm.py
diadmin/difactsheets.py
diadmin/dimock.py
diadmin/diopenlog.py
diadmin/dipmonitor.py
diadmin/dipolicy.py
diadmin/dirun.py
diadmin/ditenant.py
diadmin/diupload.py
diadmin/diuser.py
diadmin/diwsuser.py
diadmin/prepreuse.py
diadmin/prettifyJSON.py
diadmin/s3upload.py
diadmin.egg-info/PKG-INFO
diadmin.egg-info/SOURCES.txt
diadmin.egg-info/dependency_links.txt
diadmin.egg-info/entry_points.txt
diadmin.egg-info/requires.txt
diadmin.egg-info/top_level.txt
diadmin/analysis/__init__.py
diadmin/analysis/graph_policies.py
diadmin/dimockapi/__init__.py
diadmin/dimockapi/mock_api.py
diadmin/dimockapi/mock_inport.py
diadmin/metadata_api/__init__.py
diadmin/metadata_api/browse_connection.py
diadmin/metadata_api/catalog.py
diadmin/metadata_api/catalog_rdf.py
diadmin/metadata_api/connection.py
diadmin/metadata_api/container.py
diadmin/metadata_api/dataset.py
diadmin/metadata_api/dataset_rfd.py
diadmin/metadata_api/dcat_ap2_read.py
diadmin/metadata_api/dqm.py
diadmin/metadata_api/glossary.py
diadmin/metadata_api/lineage.py
diadmin/ontoviz/__init__.py
diadmin/ontoviz/graph_element.py
diadmin/ontoviz/namespace.py
diadmin/ontoviz/ontology_viz.py
diadmin/ontoviz/utils.py
diadmin/pipeline_api/__init__.py
diadmin/pipeline_api/runtime.py
diadmin/rdfutils/__init__.py
diadmin/rdfutils/add_relation.py
diadmin/rdfutils/didatasets2rdf.py
diadmin/rdfutils/pysparql.py
diadmin/rdfutils/rdf2mmd.py
diadmin/rdfutils/rdftest.py
diadmin/rdfutils/rdfvis.py
diadmin/rdfutils/sql2rdf.py
diadmin/rdfutils/thordf.py
diadmin/utils/__init__.py
diadmin/utils/genpwds.py
diadmin/utils/utils.py
diadmin/vctl_cmds/__init__.py
diadmin/vctl_cmds/login.py
diadmin/vctl_cmds/policy.py
diadmin/vctl_cmds/solution.py
diadmin/vctl_cmds/tenant.py
diadmin/vctl_cmds/user.py
diadmin/vctl_cmds/vrep.py