Metadata-Version: 2.1
Name: diadmin
Version: 0.0.74
Summary: Utility scripts for SAP Data Intelligence.
Home-page: https://github.com/thhapke/diadmin/
Author: Thorsten Hapke
Author-email: thorsten.hapke@sap.com
Project-URL: vctl, https://launchpad.support.sap.com/#/softwarecenter/template/products/%20_APP=00200682500000001943&_EVENT=DISPHIER&HEADER=Y&FUNCTIONBAR=N&EVENT=TREE&NE=NAVIGATE&ENR=73554900100800002981&V=INST&TA=ACTUAL&PAGE=SEARCH/DATA%20INTELLIGENCE-SYS%20MGMT%20CLI
Classifier: Programming Language :: Python :: 3.10
Classifier: License :: OSI Approved :: Apache Software License
Classifier: Operating System :: OS Independent
Requires-Python: >=3.10
